MANIFEST.in
README.rst
setup.py
pyodnoklassniki/__init__.py
pyodnoklassniki/errors.py
pyodnoklassniki/exceptions.py
pyodnoklassniki/requestor.py
pyodnoklassniki.egg-info/PKG-INFO
pyodnoklassniki.egg-info/SOURCES.txt
pyodnoklassniki.egg-info/dependency_links.txt
pyodnoklassniki.egg-info/requires.txt
pyodnoklassniki.egg-info/top_level.txt
pyodnoklassniki/contrib/__init__.py
pyodnoklassniki/contrib/django/__init__.py
pyodnoklassniki/contrib/django/middleware.py