Metadata-Version: 1.1
Name: pyodnoklassniki
Version: 1.0.0
Summary: Odnoklassniki REST API wrapper.
Home-page: https://github.com/marselester/pyodnoklassniki/
Author: Marsel Mavletkulov
Author-email: marselester@ya.ru
License: UNKNOWN
Platform: UNKNOWN
Classifier: Programming Language :: Python
Classifier: Programming Language :: Python :: 2.7
Classifier: Programming Language :: Python :: 3.6
